tink_http_python/__init__.py
tink_http_python/accounts.py
tink_http_python/api.py
tink_http_python/config.py
tink_http_python/exceptions.py
tink_http_python/tink.py
tink_http_python/transactions.py
tink_http_python/authentication/__init__.py
tink_http_python/authentication/api.py
tink_http_python/authentication/authentication.py
tink_http_python/authentication/storage.py
tink_http_python-1.4.10.dist-info/METADATA
tink_http_python-1.4.10.dist-info/WHEEL
tink_http_python-1.4.10.dist-info/licenses/LICENSE
tink_http_python-1.4.10.dist-info/RECORD
