Metadata-Version: 2.4
Name: tink-http-python
Version: 1.4.10
Summary: Python SDK for accessing the tink API
Author-email: José Ignacio Amelivia Santiago <hello@namelivia.com>
License-File: LICENSE
Classifier: Development Status :: 5 - Production/Stable
Classifier: Intended Audience :: Developers
Classifier: License :: OSI Approved :: MIT License
Classifier: Programming Language :: Python :: 3.8
Classifier: Programming Language :: Python :: 3.9
Classifier: Topic :: Software Development :: Build Tools
Requires-Python: <4,>=3.10
Requires-Dist: dataclass-map-and-log==0.1.6
Requires-Dist: pyhumps
Requires-Dist: requests
Requires-Dist: tink-python-api-types==0.0.13
